{
	"Wheel 1": {
		"dictName": "Wheel 1",
		"name": "Wheel",
		"customName": "wheel1",
		"type": "",
		"x": 260,
		"y": 15,
		"z": 0,
		"rx": 0,
		"ry": 0,
		"rz": -1,
		"a": 1.57
	},
	"Wheel 2": {
		"dictName": "Wheel 2",
		"name": "Wheel",
		"customName": "wheel2",
		"type": "",
		"x": -260,
		"y": 15,
		"z": 0,
		"rx": 0,
		"ry": 0,
		"rz": -1,
		"a": 1.57
	},
	"lidar": {
		"dictName": "lidar",
		"name": "Lidar",
		"customName": "lidar",
		"type": "add",
		"x": 0,
		"y": 370,
		"z": 0,
		"rx": 0,
		"ry": 1,
		"rz": 0,
		"a": 1.5708
	},
	"gps": {
		"dictName": "gps",
		"name": "GPS",
		"customName": "gps",
		"type": "add",
		"x": 0,
		"y": 0,
		"z": 0,
		"rx": 0,
		"ry": 1,
		"rz": 0,
		"a": 1.5708
	},
	"gyro": {
		"dictName": "gyro",
		"name": "Gyro",
		"customName": "gyro",
		"type": "add",
		"x": 0,
		"y": 0,
		"z": 0,
		"rx": 0,
		"ry": 1,
		"rz": 0,
		"a": 1.5708
	},
	"camera1": {
		"dictName": "camera1",
		"name": "Camera",
		"customName": "camera1",
		"type": "add",
		"x": 0,
		"y": 310,
		"z": -330,
		"rx": 0.45,
		"ry": 0.45,
		"rz": -0.77,
		"a": 1.82
	},
	"camera2": {
		"dictName": "camera2",
		"name": "Camera",
		"customName": "camera2",
		"type": "add",
		"x": 330,
		"y": 310,
		"z": 0,
		"rx": -0.94,
		"ry": 0.25,
		"rz": 0.25,
		"a": 4.65
	},
	"camera3": {
		"dictName": "camera3",
		"name": "Camera",
		"customName": "camera3",
		"type": "add",
		"x": -330,
		"y": 310,
		"z": 0,
		"rx": -0.18,
		"ry": 0.7,
		"rz": -0.69,
		"a": 2.78
	}
}